LICENSE
README.md
setup.py
pyTensileTest/__init__.py
pyTensileTest/pyTensileTest.py
pyTensileTest/teste.py
pyTensileTest.egg-info/PKG-INFO
pyTensileTest.egg-info/SOURCES.txt
pyTensileTest.egg-info/dependency_links.txt
pyTensileTest.egg-info/requires.txt
pyTensileTest.egg-info/top_level.txt