Metadata-Version: 2.1
Name: pyTensileTest
Version: 0.0.5
Summary: A package for manipulating tensile test data, creating and correcting stress-strain diagrams.
Home-page: https://github.com/GabrielVZanata/pyTensileTest
Author: Gabriel Valverde Zanata da Silva
Author-email: gabriel.valverde@hotmail.com
License: MIT License
Keywords: shimadzu tensile test
Platform: UNKNOWN
License-File: LICENSE
